OmicsIntegrator/__init__.py
OmicsIntegrator/__main__.py
OmicsIntegrator/graph.py
OmicsIntegrator/gslr_macro.py
OmicsIntegrator/annotation/final_annotation.pickle
OmicsIntegrator-2.3.10.dist-info/LICENSE
OmicsIntegrator-2.3.10.dist-info/METADATA
OmicsIntegrator-2.3.10.dist-info/WHEEL
OmicsIntegrator-2.3.10.dist-info/entry_points.txt
OmicsIntegrator-2.3.10.dist-info/top_level.txt
OmicsIntegrator-2.3.10.dist-info/RECORD
